zeromessage/__init__.py
zeromessage/envelop_socket.py
zeromessage-0.2.dist-info/METADATA
zeromessage-0.2.dist-info/WHEEL
zeromessage-0.2.dist-info/entry_points.txt
zeromessage-0.2.dist-info/top_level.txt
zeromessage-0.2.dist-info/RECORD
