Metadata-Version: 2.1
Name: zeromessage
Version: 0.2
Summary: Lightweight ROS-like pub-sub tool utilizing ZeroMQ
Home-page: https://github.com/yodahuang/zero-message
Author: Yanda Huang
Author-email: yord.huang@gmail.com
License: MIT
Platform: UNKNOWN
Requires-Dist: zmq
Requires-Dist: fire
